bunkrwallet/__init__.py
bunkrwallet/btc.py
bunkrwallet/wallet.py
bunkrwallet-0.3.1.data/scripts/bunkr-wallet
bunkrwallet-0.3.1.dist-info/LICENSE
bunkrwallet-0.3.1.dist-info/METADATA
bunkrwallet-0.3.1.dist-info/WHEEL
bunkrwallet-0.3.1.dist-info/top_level.txt
bunkrwallet-0.3.1.dist-info/RECORD
