Metadata-Version: 2.1
Name: bunkrwallet
Version: 0.3.1
Summary: Lite bitcoin bunkr-wallet working on top of Bunkr secrets
Home-page: UNKNOWN
Author: off-the-grid-inc
Author-email: accounts@off-the-grid.io
License: UNKNOWN
Platform: UNKNOWN
Classifier: Programming Language :: Python :: 3.6
Classifier: Operating System :: OS Independent
Requires-Dist: ecdsa (>=0.13.2)
Requires-Dist: python-bitcoinlib (>=0.10.1)
Requires-Dist: requests (>=2.22.0)
Requires-Dist: punkr (>=1.0)
